tests/__init__.py
tests/test_build_tree.py
tests/test_cases.py
tests/test_extract.py
tests/test_nlp.py
tests/test_summarize.py
txt2hpo/__init__.py
txt2hpo/build_tree.py
txt2hpo/config.py
txt2hpo/extract.py
txt2hpo/extract_.py
txt2hpo/nlp.py
txt2hpo/spellcheck.py
txt2hpo/summarize.py
txt2hpo/util.py
txt2hpo/data/__init__.py
txt2hpo/data/doc2vec_dm0_tagUniq_ep51_sa1e-05_vs40_ws18_mc5_neg5.wv.gz
txt2hpo/data/spellcheck_vocab_upd032020.json
txt2hpo-2021.0.dist-info/LICENSE
txt2hpo-2021.0.dist-info/METADATA
txt2hpo-2021.0.dist-info/WHEEL
txt2hpo-2021.0.dist-info/entry_points.txt
txt2hpo-2021.0.dist-info/top_level.txt
txt2hpo-2021.0.dist-info/RECORD
