Metadata-Version: 2.1
Name: txt2hpo
Version: 2021.0
Summary: HPO concept recognition and phenotype extraction tool
Author: Vlad Gainullin <vgainullin@genedx.com>, Kevin Arvai <karvai@genedx.com>
Author-email: <datascience@genedx.com>
License: UNKNOWN
Platform: UNKNOWN
License-File: LICENSE
Requires-Dist: pandas
Requires-Dist: nltk (==3.4.5)
Requires-Dist: spacy (==2.2.4)
Requires-Dist: scispacy (==0.2.4)
Requires-Dist: negspacy (==0.1.9)
Requires-Dist: networkx
Requires-Dist: obonet
Requires-Dist: requests
Requires-Dist: gensim (==3.8.1)
